algomath_def/__init__.py
algomath_def/module01.py
algomath_def-0.0.1.dist-info/METADATA
algomath_def-0.0.1.dist-info/WHEEL
algomath_def-0.0.1.dist-info/top_level.txt
algomath_def-0.0.1.dist-info/RECORD
