Metadata-Version: 2.1
Name: algomath-def
Version: 0.0.1
Summary: algomath_def:Libraries of each major function for algorithmic understanding,and for learning Github and learning Python 
Home-page: https://github.com/yuichi-shindo/test
Download-URL: https://github.com/yuichi-shindo/test
Author: Yuichi Shindo
Author-email: chiru9.shindou@gmail.com
Maintainer: Yuichi Shindo
Maintainer-email: chiru9.shindou@gmail.com
License: MIT Licence
Classifier: License :: OSI Approved :: MIT License
Classifier: Programming Language :: Python :: 3
Classifier: Programming Language :: Python :: 3.6
Classifier: Programming Language :: Python :: 3.7
Classifier: Programming Language :: Python :: 3.8
Classifier: Programming Language :: Python :: 3.9
Classifier: Programming Language :: Python :: 3 :: Only
Requires-Python: >=3.6
